CHANGELOG.txt
LICENSE
MANIFEST.in
README.rst
rpi_ws281x_wrap.c
setup.py
version.h
lib/LICENSE
lib/clk.h
lib/dma.c
lib/dma.h
lib/gpio.h
lib/mailbox.c
lib/mailbox.h
lib/main.c
lib/pcm.c
lib/pcm.h
lib/pwm.c
lib/pwm.h
lib/rpihw.c
lib/rpihw.h
lib/ws2811.c
lib/ws2811.h
rpi_ws281x/__init__.py
rpi_ws281x/rpi_ws281x.py
rpi_ws281x_3bp_spi1.egg-info/PKG-INFO
rpi_ws281x_3bp_spi1.egg-info/SOURCES.txt
rpi_ws281x_3bp_spi1.egg-info/dependency_links.txt
rpi_ws281x_3bp_spi1.egg-info/top_level.txt