Metadata-Version: 2.1
Name: rpi-ws281x-3bp-spi1
Version: 0.0.1
Summary: Userspace Raspberry Pi PWM/PCM/SPI library for SK6812 and WS281X LEDs.
Home-page: https://github.com/P13R3/rpi-ws281x-python-3bp_spi1
Author: Jeremy Garff <jer@jers.net>, Phil Howard <phil@pimoroni.com>
Author-email: jer@jers.net, phil@pimoroni.com
License: MIT
Platform: UNKNOWN
License-File: LICENSE
